[
    {"row": [
        {"value": "\ud834\udee0", "action": "char", "src": "./assets/characters/maya/1.png"},
        {"value": "\ud834\udee1", "action": "char", "src": "./assets/characters/maya/2.png"},
        {"value": "\ud834\udee2", "action": "char", "src": "./assets/characters/maya/3.png"},
        {"value": "\ud834\udee3", "action": "char", "src": "./assets/characters/maya/4.png"},
        {"value": "\ud834\udee4", "action": "char", "src": "./assets/characters/maya/5.png"},
        {"value": "\ud834\udee5", "action": "char", "src": "./assets/characters/maya/6.png"},
        {"value": "\ud834\udee6", "action": "char", "src": "./assets/characters/maya/7.png"},
        {"value": "\ud834\udee7", "action": "char", "src": "./assets/characters/maya/8.png"},
        {"value": "\ud834\udee8", "action": "char", "src": "./assets/characters/maya/9.png"},
        {"value": "\ud834\udee9", "action": "char", "src": "./assets/characters/maya/10.png"},
        {"value": "'", "action": "char"},
        {"value": "\"", "action": "char"},
        {"value": "!", "action": "char"},
        {"value": "?", "action": "char"},        
        {"value": "⿰", "action": "char"},
        {"value": "⿱", "action": "char"},
        {"value": "⿲", "action": "char"},
        {"value": "⿳", "action": "char"},
        {"value": "⿴", "action": "char"},
        {"value": "⿵", "action": "char"}
    ]},
    {"row": [
        {"value": "\ud834\udeea", "action": "char", "src": "./assets/characters/maya/11.png"},
        {"value": "\ud834\udeeb", "action": "char", "src": "./assets/characters/maya/12.png"},
        {"value": "\ud834\udeec", "action": "char", "src": "./assets/characters/maya/13.png"},
        {"value": "\ud834\udeed", "action": "char", "src": "./assets/characters/maya/14.png"},
        {"value": "\ud834\udeee", "action": "char", "src": "./assets/characters/maya/15.png"},
        {"value": "\ud834\udeef", "action": "char", "src": "./assets/characters/maya/16.png"},
        {"value": "\ud834\udef0", "action": "char", "src": "./assets/characters/maya/17.png"},
        {"value": "\ud834\udef1", "action": "char", "src": "./assets/characters/maya/18.png"},
        {"value": "\ud834\udef2", "action": "char", "src": "./assets/characters/maya/19.png"},
        {"value": "\ud834\udef3", "action": "char", "src": "./assets/characters/maya/20.png"},
        {"value": "+", "action": "char"},
        {"value": "-", "action": "char"},
        {"value": "*", "action": "char"},
        {"value": "/", "action": "char"},
        {"value": "⿶", "action": "char"},
        {"value": "⿷", "action": "char"},
        {"value": "⿸", "action": "char"},
        {"value": "⿹", "action": "char"},
        {"value": "⿺", "action": "char"},
        {"value": "⿻", "action": "char"}
    ]},
    {"row":[
        {"value": "a", "action": "char", "src": "./assets/characters/maya/21.png"},
        {"value": "ba", "action": "char", "src": "./assets/characters/maya/26.png"},
        {"value": "cha", "action": "char", "src": "./assets/characters/maya/31.png"},
        {"value": "ch'a", "action": "char", "src": "./assets/characters/maya/36.png"},
        {"value": "ha", "action": "char", "src": "./assets/characters/maya/38.png"},
        {"value": "ja", "action": "char", "type": "unused"},
        {"value": "ka", "action": "char", "src": "./assets/characters/maya/43.png"},
        {"value": "k'a", "action": "char", "src": "./assets/characters/maya/48.png"},
        {"value": "la", "action": "char", "src": "./assets/characters/maya/51.png"},
        {"value": "ma", "action": "char", "src": "./assets/characters/maya/56.png"},
        {"value": "na", "action": "char", "src": "./assets/characters/maya/61.png"},
        {"value": "pa", "action": "char", "src": "./assets/characters/maya/65.png"},
        {"value": "p'a", "action": "char", "type": "unused"},
        {"value": "sa", "action": "char", "src": "./assets/characters/maya/72.png"},
        {"value": "ta", "action": "char", "src": "./assets/characters/maya/76.png"},
        {"value": "t'a", "action": "char", "type": "unused"},
        {"value": "tza", "action": "char", "src": "./assets/characters/maya/83.png"},
        {"value": "tz'a", "action": "char", "src": "./assets/characters/maya/87.png"},
        {"value": "wa", "action": "char", "src": "./assets/characters/maya/90.png"},
        {"value": "xa", "action": "char", "src": "./assets/characters/maya/93.png"},
        {"value": "ya", "action": "char", "src": "./assets/characters/maya/98.png"}
    ]},
    {"row":[
        {"value": "e", "action": "char", "src": "./assets/characters/maya/22.png"},
        {"value": "be", "action": "char", "src": "./assets/characters/maya/27.png"},
        {"value": "che", "action": "char", "src": "./assets/characters/maya/32.png"},
        {"value": "ch'e", "action": "char", "type": "unused"},
        {"value": "he", "action": "char", "src": "./assets/characters/maya/39.png"},
        {"value": "je", "action": "char", "type": "unused"},
        {"value": "ke", "action": "char", "src": "./assets/characters/maya/44.png"},
        {"value": "k'e", "action": "char", "type": "unused"},
        {"value": "le", "action": "char", "src": "./assets/characters/maya/52.png"},
        {"value": "me", "action": "char", "src": "./assets/characters/maya/57.png"},
        {"value": "ne", "action": "char", "src": "./assets/characters/maya/62.png"},
        {"value": "pe", "action": "char", "src": "./assets/characters/maya/66.png"},
        {"value": "p'e", "action": "char", "src": "./assets/characters/maya/70.png"},
        {"value": "se", "action": "char", "src": "./assets/characters/maya/73.png"},
        {"value": "te", "action": "char", "src": "./assets/characters/maya/77.png"},
        {"value": "t'e", "action": "char", "src": "./assets/characters/maya/81.png"},
        {"value": "tze", "action": "char", "src": "./assets/characters/maya/84.png"},
        {"value": "tz'e", "action": "char", "type": "unused"},
        {"value": "we", "action": "char", "type": "unused"},
        {"value": "xe", "action": "char", "src": "./assets/characters/maya/94.png"},
        {"value": "ye", "action": "char", "src": "./assets/characters/maya/99.png"}
    ]},
    {"row":[
        {"value": "i", "action": "char", "src": "./assets/characters/maya/23.png"},
        {"value": "bi", "action": "char", "src": "./assets/characters/maya/28.png"},
        {"value": "chi", "action": "char", "src": "./assets/characters/maya/33.png"},
        {"value": "ch'i", "action": "char", "type": "unused"},
        {"value": "hi", "action": "char", "src": "./assets/characters/maya/40.png"},
        {"value": "ji", "action": "char", "type": "unused"},
        {"value": "ki", "action": "char", "src": "./assets/characters/maya/45.png"},
        {"value": "k'i", "action": "char", "type": "unused"},
        {"value": "li", "action": "char", "src": "./assets/characters/maya/53.png"},
        {"value": "mi", "action": "char", "src": "./assets/characters/maya/58.png"},
        {"value": "ni", "action": "char", "src": "./assets/characters/maya/63.png"},
        {"value": "pi", "action": "char", "src": "./assets/characters/maya/67.png"},
        {"value": "p'i", "action": "char", "src": "./assets/characters/maya/71.png"},
        {"value": "si", "action": "char", "src": "./assets/characters/maya/74.png"},
        {"value": "ti", "action": "char", "src": "./assets/characters/maya/78.png"},
        {"value": "t'i", "action": "char", "type": "unused"},
        {"value": "tzi", "action": "char", "src": "./assets/characters/maya/85.png"},
        {"value": "tz'i", "action": "char", "src": "./assets/characters/maya/88.png"},
        {"value": "wi", "action": "char", "src": "./assets/characters/maya/91.png"},
        {"value": "xi", "action": "char", "src": "./assets/characters/maya/95.png"},
        {"value": "yi", "action": "char", "src": "./assets/characters/maya/100.png"}
    ]},
    {"row":[
        {"value": "o", "action": "char", "src": "./assets/characters/maya/24.png"},
        {"value": "bo", "action": "char", "src": "./assets/characters/maya/29.png"},
        {"value": "cho", "action": "char", "src": "./assets/characters/maya/34.png"},
        {"value": "ch'o", "action": "char", "src": "./assets/characters/maya/37.png"},
        {"value": "ho", "action": "char", "src": "./assets/characters/maya/41.png"},
        {"value": "jo", "action": "char", "type": "unused"},
        {"value": "ko", "action": "char", "src": "./assets/characters/maya/46.png"},
        {"value": "k'o", "action": "char", "src": "./assets/characters/maya/49.png"},
        {"value": "lo", "action": "char", "src": "./assets/characters/maya/54.png"},
        {"value": "mo", "action": "char", "src": "./assets/characters/maya/59.png"},
        {"value": "no", "action": "char", "type": "unused"},
        {"value": "po", "action": "char", "src": "./assets/characters/maya/68.png"},
        {"value": "p'o", "action": "char", "type": "unused"},
        {"value": "so", "action": "char", "type": "unused"},
        {"value": "to", "action": "char", "src": "./assets/characters/maya/79.png"},
        {"value": "t'o", "action": "char", "type": "unused"},
        {"value": "tzo", "action": "char","type": "unused"},
        {"value": "tz'o", "action": "char", "type": "unused"},
        {"value": "wo", "action": "char", "src": "./assets/characters/maya/92.png"},
        {"value": "xo", "action": "char", "src": "./assets/characters/maya/96.png"},
        {"value": "yo", "action": "char", "src": "./assets/characters/maya/101.png"}
    ]},
    {"row":[
        {"value": "u", "action": "char", "src": "./assets/characters/maya/25.png"},
        {"value": "bu", "action": "char", "src": "./assets/characters/maya/30.png"},
        {"value": "chu", "action": "char", "src": "./assets/characters/maya/35.png"},
        {"value": "ch'u", "action": "char", "type": "unused"},
        {"value": "hu", "action": "char", "src": "./assets/characters/maya/42.png"},
        {"value": "ju", "action": "char", "type": "unused"},
        {"value": "ku", "action": "char", "src": "./assets/characters/maya/47.png"},
        {"value": "k'u", "action": "char", "src": "./assets/characters/maya/50.png"},
        {"value": "lu", "action": "char", "src": "./assets/characters/maya/55.png"},
        {"value": "mu", "action": "char", "src": "./assets/characters/maya/60.png"},
        {"value": "nu", "action": "char", "src": "./assets/characters/maya/64.png"},
        {"value": "pu", "action": "char", "src": "./assets/characters/maya/69.png"},
        {"value": "p'u", "action": "char", "type": "unused"},
        {"value": "su", "action": "char", "src": "./assets/characters/maya/75.png"},
        {"value": "tu", "action": "char", "src": "./assets/characters/maya/80.png"},
        {"value": "t'u", "action": "char", "src": "./assets/characters/maya/82.png"},
        {"value": "tzu", "action": "char", "src": "./assets/characters/maya/86.png"},
        {"value": "tz'u", "action": "char", "src": "./assets/characters/maya/89.png"},
        {"value": "wu", "action": "char", "type": "unused"},
        {"value": "xu", "action": "char", "src": "./assets/characters/maya/97.png"},
        {"value": "yu", "action": "char", "src": "./assets/characters/maya/102.png"}
    ]},
    {"row":[
        {"value": "\u00A0", "action": "space"},
        {"value": "chan", "action": "char", "src": "./assets/characters/maya/103.png"},
        {"value": "bih", "action": "char", "src": "./assets/characters/maya/104.png"},
        {"value": "tun", "action": "char", "src": "./assets/characters/maya/105.png"},
        {"value": "na", "action": "char", "src": "./assets/characters/maya/106.png"},
        {"value": "nik", "action": "char", "src": "./assets/characters/maya/107.png"},
        {"value": "bak", "action": "char", "src": "./assets/characters/maya/108.png"},
        {"value": "balam", "action": "char", "src": "./assets/characters/maya/109.png"},
        {"value": "\u23CE", "action": "enter"}
    ]},
    {"rowVert":[
        {"value": "a", "action": "char", "src": "./assets/characters/maya/1.png"},
        {"value": "e", "action": "char", "src": "./assets/characters/maya/1.png"},
        {"value": "i", "action": "char", "src": "./assets/characters/maya/1.png"},
        {"value": "o", "action": "char", "src": "./assets/characters/maya/1.png"},
        {"value": "u", "action": "char", "src": "./assets/characters/maya/1.png"}
    ]},
    {"rowVert":[
        {"value": "カ", "action": "char", "src": "./assets/characters/maya/1.png"},
        {"value": "キ", "action": "char", "src": "./assets/characters/maya/1.png"},
        {"value": "ク", "action": "char", "src": "./assets/characters/maya/1.png"},
        {"value": "ケ", "action": "char", "src": "./assets/characters/maya/1.png"},
        {"value": "コ", "action": "char", "src": "./assets/characters/maya/1.png"}
    ]},
    {"rowVert": [
        {"value": "ガ", "action": "char", "src": "./assets/characters/maya/1.png"},
        {"value": "ギ", "action": "char", "src": "./assets/characters/maya/1.png"},
        {"value": "グ", "action": "char", "src": "./assets/characters/maya/1.png"},
        {"value": "ゲ", "action": "char", "src": "./assets/characters/maya/1.png"},
        {"value": "ゴ", "action": "char", "src": "./assets/characters/maya/1.png"}
    ]},
    {"rowVert": [
        {"value": "サ", "action": "char", "src": "./assets/characters/maya/1.png"},
        {"value": "シ", "action": "char", "src": "./assets/characters/maya/1.png"},
        {"value": "ス", "action": "char", "src": "./assets/characters/maya/1.png"},
        {"value": "セ", "action": "char", "src": "./assets/characters/maya/1.png"},
        {"value": "ソ", "action": "char", "src": "./assets/characters/maya/1.png"}
    ]},
    {"rowVert": [
        {"value": "ザ", "action": "char", "src": "./assets/characters/maya/1.png"},
        {"value": "ジ", "action": "char", "src": "./assets/characters/maya/1.png"},
        {"value": "ズ", "action": "char", "src": "./assets/characters/maya/1.png"},
        {"value": "ゼ", "action": "char", "src": "./assets/characters/maya/1.png"},
        {"value": "ゾ", "action": "char", "src": "./assets/characters/maya/1.png"}
    ]},
    {"rowVert": [
        {"value": "タ", "action": "char", "src": "./assets/characters/maya/1.png"},
        {"value": "チ", "action": "char", "src": "./assets/characters/maya/1.png"},
        {"value": "ツ", "action": "char", "src": "./assets/characters/maya/1.png"},
        {"value": "テ", "action": "char", "src": "./assets/characters/maya/1.png"},
        {"value": "ト", "action": "char", "src": "./assets/characters/maya/1.png"}
    ]},
    {"rowVert":[
        {"value": "ダ", "action": "char", "src": "./assets/characters/maya/1.png"},
        {"value": "ヂ", "action": "char", "src": "./assets/characters/maya/1.png"},
        {"value": "ヅ", "action": "char", "src": "./assets/characters/maya/1.png"},
        {"value": "デ", "action": "char", "src": "./assets/characters/maya/1.png"},
        {"value": "ド", "action": "char", "src": "./assets/characters/maya/1.png"}
    ]},
    {"rowVert": [
        {"value": "ナ", "action": "char", "src": "./assets/characters/maya/1.png"},
        {"value": "ニ", "action": "char", "src": "./assets/characters/maya/1.png"},
        {"value": "ヌ", "action": "char", "src": "./assets/characters/maya/1.png"},
        {"value": "ネ", "action": "char", "src": "./assets/characters/maya/1.png"},
        {"value": "ノ", "action": "char", "src": "./assets/characters/maya/1.png"}
    ]},
    {"rowVert":[
        {"value": "ハ", "action": "char", "src": "./assets/characters/maya/1.png"},
        {"value": "ヒ", "action": "char", "src": "./assets/characters/maya/1.png"},
        {"value": "フ", "action": "char", "src": "./assets/characters/maya/1.png"},
        {"value": "ヘ", "action": "char", "src": "./assets/characters/maya/1.png"},
        {"value": "ホ", "action": "char", "src": "./assets/characters/maya/1.png"}
    ]},
    {"rowVert": [
        {"value": "バ", "action": "char", "src": "./assets/characters/maya/1.png"},
        {"value": "ビ", "action": "char", "src": "./assets/characters/maya/1.png"},
        {"value": "ブ", "action": "char", "src": "./assets/characters/maya/1.png"},
        {"value": "ベ", "action": "char", "src": "./assets/characters/maya/1.png"},
        {"value": "ボ", "action": "char", "src": "./assets/characters/maya/1.png"}
    ]},
    {"rowVert":[
        {"value": "パ", "action": "char", "src": "./assets/characters/maya/1.png"},
        {"value": "ピ", "action": "char", "src": "./assets/characters/maya/1.png"},
        {"value": "プ", "action": "char", "src": "./assets/characters/maya/1.png"},
        {"value": "ペ", "action": "char", "src": "./assets/characters/maya/1.png"},
        {"value": "ポ", "action": "char", "src": "./assets/characters/maya/1.png"}
    ]},
    {"rowVert": [
        {"value": "マ", "action": "char", "src": "./assets/characters/maya/1.png"},
        {"value": "ミ", "action": "char", "src": "./assets/characters/maya/1.png"},
        {"value": "ム", "action": "char", "src": "./assets/characters/maya/1.png"},
        {"value": "メ", "action": "char", "src": "./assets/characters/maya/1.png"},
        {"value": "モ", "action": "char", "src": "./assets/characters/maya/1.png"}
    ]},
    {"rowVert":[
        {"value": "ヤ", "action": "char", "src": "./assets/characters/maya/1.png"},
        {"value": "\u00A0", "action": "char", "src": "./assets/characters/maya/1.png"},
        {"value": "ユ", "action": "char", "src": "./assets/characters/maya/1.png"},
        {"value": "エ", "action": "char", "src": "./assets/characters/maya/1.png", "type": "unused"},
        {"value": "ヨ", "action": "char", "src": "./assets/characters/maya/1.png"}
    ]},
    {"rowVert":[
        {"value": "ラ", "action": "char", "src": "./assets/characters/maya/1.png"},
        {"value": "リ", "action": "char", "src": "./assets/characters/maya/1.png"},
        {"value": "ル", "action": "char", "src": "./assets/characters/maya/1.png"},
        {"value": "レ", "action": "char", "src": "./assets/characters/maya/1.png"},
        {"value": "ロ", "action": "char", "src": "./assets/characters/maya/1.png"}
    ]},
    {"rowVert":[
        {"value": "ワ", "action": "char", "src": "./assets/characters/maya/1.png"},
        {"value": "ヰ", "action": "char", "src": "./assets/characters/maya/1.png", "type": "unused"},
        {"value": "\u00A0", "action": "char", "src": "./assets/characters/maya/1.png"},
        {"value": "ヱ", "action": "char", "src": "./assets/characters/maya/1.png", "type": "unused"},
        {"value": "ヲ", "action": "char", "src": "./assets/characters/maya/1.png"}
    ]},
    {"rowVert":[
        {"value": "ン", "action": "char", "src": "./assets/characters/maya/1.png"},
        {"value": "ッ", "action": "char", "src": "./assets/characters/maya/1.png"},
        {"value": "ヽ", "action": "char", "src": "./assets/characters/maya/1.png"},
        {"value": "゛", "action": "char", "src": "./assets/characters/maya/1.png"},
        {"value": "゜", "action": "char", "src": "./assets/characters/maya/1.png"}
    ]}
]
